{
  "extension.displayName": "Light Bookmarks",
  "extension.description": "ตัวจัดการที่คั่นหน้าแบบเบาสำหรับ VSCode พร้อมการรองรับคอลเลกชัน",
  "configuration.title": "Light Bookmarks",
  "configuration.showLineNumbers.description": "แสดงหมายเลขบรรทัดในมุมมองที่คั่นหน้า",
  "configuration.maxBookmarksPerFile.description": "จำนวนที่คั่นหน้าสูงสุดต่อไฟล์",
  "command.toggleBookmark.title": "สลับที่คั่นหน้า",
  "command.createCollection.title": "สร้างคอลเลกชัน",
  "command.deleteCollection.title": "ลบคอลเลกชัน",
  "command.moveCollectionUp.title": "ย้ายคอลเลกชันขึ้น",
  "command.moveCollectionDown.title": "ย้ายคอลเลกชันลง",
  "command.editBookmarkDescription.title": "แก้ไขคำอธิบาย",
  "command.addBookmarkToCollection.title": "เพิ่มในคอลเลกชัน",
  "command.deleteBookmark.title": "ลบที่คั่นหน้า",
  "command.moveBookmarkUp.title": "ย้ายที่คั่นหน้าขึ้น",
  "command.moveBookmarkDown.title": "ย้ายที่คั่นหน้าลง",
  "command.collapseAll.title": "ย่อทั้งหมด",
  "command.openSettings.title": "เปิดการตั้งค่าที่คั่นหน้า",
  "command.goToNextBookmark.title": "ไปยังที่คั่นหน้าถัดไป",
  "command.goToPreviousBookmark.title": "ไปยังที่คั่นหน้าก่อนหน้า",
  "command.exportBookmarks.title": "ส่งออกที่คั่นหน้า",
  "command.importBookmarks.title": "นำเข้าที่คั่นหน้า",
  "command.category": "Light Bookmarks",
  "viewsContainers.bookmarks.title": "ที่คั่นหน้า",
  "views.bookmarks.name": "ที่คั่นหน้า"
} 